reecapi/__init__.py
reecapi/constants.py
reecapi/getters.py
tests/__init__.py
tests/test_getters.py
reecapi-0.0.2.dist-info/METADATA
reecapi-0.0.2.dist-info/WHEEL
reecapi-0.0.2.dist-info/top_level.txt
reecapi-0.0.2.dist-info/RECORD
