Metadata-Version: 2.1
Name: reecapi
Version: 0.0.2
Summary: Library to access to the data offered by the 'Registro Español de Estudios Clínicos'
Home-page: https://github.com/luisgasco/REECapi/
Author: Luis Gascó
Author-email: luisgascosanchez@gmail.com
License: UNKNOWN
Platform: UNKNOWN
Classifier: Programming Language :: Python :: 3
Classifier: License :: OSI Approved :: MIT License
Classifier: Operating System :: OS Independent
Requires-Dist: requests (>=2.22.0)
